{
  "employees": [
    {
      "id": 1,
      "employeeId": "ETA-0001",
      "name": "Alice Johnson",
      "email": "alice.johnson@example.com",
      "phone": "1234567890",
      "password": "password123",
      "status": "active",
      "position": "Software Engineer",
      "user_type": 1,
      "profile_photo": "../assets/icon1.png",
      "birthday": "1990-01-15"
    },
    {
      "id": 2,
      "employeeId": "ETA-0002",
      "name": "Bob Smith",
      "email": "bob.smith@example.com",
      "phone": "1234567891",
      "password": "password123",
      "status": "active",
      "position": "Project Manager",
      "user_type": 1,
      "profile_photo": "../assets/ETA-0001.jpg",
      "birthday": "1985-03-22"
    },
    {
      "id": 3,
      "employeeId": "ETA-0003",
      "name": "Charlie Brown",
      "email": "charlie.brown@example.com",
      "phone": "1234567892",
      "password": "password123",
      "status": "inactive",
      "position": "QA Tester",
      "user_type": 1,
      "profile_photo": "../assets/profile/ETA-0001.jpg",
      "birthday": "1992-07-10"
    },
    {
      "id": 4,
      "employeeId": "ETA-0004",
      "name": "Diana Prince",
      "email": "diana.prince@example.com",
      "phone": "1234567893",
      "password": "password123",
      "status": "active",
      "position": "Business Analyst",
      "user_type": 1,
      "profile_photo": "../assets/profile/ETA-0001.jpg",
      "birthday": "1988-12-05"
    },
    {
      "id": 5,
      "employeeId": "ETA-0005",
      "name": "Edward White",
      "email": "edward.white@example.com",
      "phone": "1234567894",
      "password": "password123",
      "status": "active",
      "position": "DevOps Engineer",
      "user_type": 1,
      "profile_photo": "../assets/profile/ETA-0001.jpg",
      "birthday": "1991-09-17"
    },
    {
      "id": 6,
      "employeeId": "KAS-0001",
      "name": "Fiona Green",
      "email": "fiona.green@example.com",
      "phone": "1234567895",
      "password": "password123",
      "status": "active",
      "position": "HR Specialist",
      "user_type": 1,
      "profile_photo": "../assets/profile/ETA-0001.jpg",
      "birthday": "1986-05-30"
    },
    {
      "id": 7,
      "employeeId": "KAS-0002",
      "name": "George Hall",
      "email": "george.hall@example.com",
      "phone": "1234567896",
      "password": "password123",
      "status": "inactive",
      "position": "Recruiter",
      "user_type": 1,
      "profile_photo": "../assets/profile/ETA-0001.jpg",
      "birthday": "1993-04-15"
    },
    {
      "id": 8,
      "employeeId": "KAS-0003",
      "name": "Hannah Lee",
      "email": "hannah.lee@example.com",
      "phone": "1234567897",
      "password": "password123",
      "status": "active",
      "position": "HR Manager",
      "user_type": 0,
      "profile_photo": "../assets/profile/ETA-0001.jpg",
      "birthday": "1987-11-25"
    },
    {
      "id": 9,
      "employeeId": "KAS-0004",
      "name": "Ian Black",
      "email": "ian.black@example.com",
      "phone": "1234567898",
      "password": "password123",
      "status": "active",
      "position": "Training Coordinator",
      "user_type": 1,
      "profile_photo": "../assets/profile/ETA-0001.jpg",
      "birthday": "1994-08-09"
    },
    {
      "id": 10,
      "employeeId": "KAS-0005",
      "name": "Jane King",
      "email": "jane.king@example.com",
      "phone": "1234567899",
      "password": "password123",
      "status": "inactive",
      "position": "HR Analyst",
      "user_type": 1,
      "profile_photo": "../assets/profile/ETA-0001.jpg",
      "birthday": "1989-06-18"
    },
    {
      "id": 11,
      "employeeId": "ETI-0001",
      "name": "Kevin Adams",
      "email": "kevin.adams@example.com",
      "phone": "9876543210",
      "password": "password123",
      "status": "active",
      "position": "IT Support",
      "user_type": 1,
      "profile_photo": "../assets/profile/ETA-0001.jpg",
      "birthday": "1990-10-03"
    },
    {
      "id": 12,
      "employeeId": "ETI-0002",
      "name": "Laura Palmer",
      "email": "laura.palmer@example.com",
      "phone": "9876543211",
      "password": "password123",
      "status": "active",
      "position": "Network Administrator",
      "user_type": 1,
      "profile_photo": "../assets/profile/ETA-0001.jpg",
      "birthday": "1984-02-20"
    },
    {
      "id": 13,
      "employeeId": "ETI-0003",
      "name": "Michael Scott",
      "email": "michael.scott@example.com",
      "phone": "9876543212",
      "password": "password123",
      "status": "inactive",
      "position": "IT Manager",
      "user_type": 0,
      "profile_photo": "",
      "birthday": "1983-09-12"
    },
    {
      "id": 14,
      "employeeId": "ETI-0004",
      "name": "Nancy Drew",
      "email": "nancy.drew@example.com",
      "phone": "9876543213",
      "password": "password123",
      "status": "active",
      "position": "Database Administrator",
      "user_type": 1,
      "profile_photo": "",
      "birthday": "1995-01-08"
    },
    {
      "id": 15,
      "employeeId": "ETI-0005",
      "name": "Oscar Wilde",
      "email": "oscar.wilde@example.com",
      "phone": "9876543214",
      "password": "password123",
      "status": "active",
      "position": "System Analyst",
      "user_type": 1,
      "profile_photo": "",
      "birthday": "1991-12-22"
    }
  ]
}
